[
{"name":"Feuerkäfer des Erwachens","beschreibung":"Die erzeugte Hitze sorgt dafür, dass du nie wieder morgens verschläfst.","bild":"Artikelbilder/Artikel01.png","preis":49.99,"kategorie":"gesundheit"},
{"name":"Freiheitstropfen des Lebens","beschreibung":"Befreit dich sofort von einer Krankheit oder Verletzung deiner Wahl.","bild":"Artikelbilder/Artikel02.png","preis":119.99,"kategorie":"gesundheit"},
{"name":"Mondsichel-Messer","beschreibung":"Ein magisches Messer, welches deine Frisur bei Vollmond automatisch perfekt schneidet.","bild":"Artikelbilder/Artikel03.png","preis":64.99,"kategorie":"gesundheit"},
{"name":"Herz der Lebenskraft","beschreibung":"Katzen haben sieben Leben? Mit diesem Medallion hast du nun zwei.","bild":"Artikelbilder/Artikel04.png","preis":799.99,"kategorie":"gesundheit"},
{"name":"Totem der Verwandlung","beschreibung":"Verwandelt den Anwender für 24 Stunden in eine Katze. Rasse und Geschlecht wählbar.","bild":"Artikelbilder/Artikel11.png","preis":189.99,"kategorie":"gesundheit"},
{"name":"Auge der 4. Dimension","beschreibung":"Deine Sicht wird um 400% verbessert. Extreme Weitsicht, Nachtsicht & Wärmebildsicht inkl.","bild":"Artikelbilder/Artikel06.png","preis":419.99,"kategorie":"gesundheit"},
{"name":"Metallischer Mondorden","beschreibung":"Lädt deine Hände und Füße magnetisch auf, um an Metalwänden zu klettern.","bild":"Artikelbilder/Artikel13.png","preis":84.99,"kategorie":"gesundheit"},
{"name":"Shurikenstern der Vitalität","beschreibung":"Erhört für 72h deine Stärke, Flexibilität & Schnelligkeit um 300%. Wie ein Ninja.","bild":"Artikelbilder/Artikel16.png","preis":349.99,"kategorie":"gesundheit"},
{"name":"Kristall der wärmenden Sonne","beschreibung":"Verwandelt Pessimisten in Optimisten. Bis zu 5mal anwendbar.","bild":"Artikelbilder/Artikel05.png","preis":79.99,"kategorie":"mana"},
{"name":"Golddiadem der Erlösung","beschreibung":"Hebt Hausarrest der Eltern auf. Kann nur einmal verwendet werden.","bild":"Artikelbilder/Artikel07.png","preis":49.99,"kategorie":"mana"},
{"name":"Stein des Bildungserfolgs","beschreibung":"Lässt dich mit 100% jede Prüfung bestehen. Effekt verfliegt nach 365 Tagen.","bild":"Artikelbilder/Artikel08.png","preis":549.99,"kategorie":"mana"},
{"name":"Vermächtnis der Lotusblüte","beschreibung":"Wäscht dein Gedächtnis rein von unbrauchbarem Wissen.","bild":"Artikelbilder/Artikel09.png","preis":34.99,"kategorie":"mana"},
{"name":"Messertanz der Genauigkeit","beschreibung":"Nimmt einem Klugscheißer die Fähigkeit alles besser zu wissen.","bild":"Artikelbilder/Artikel10.png","preis":279.99,"kategorie":"mana"},
{"name":"Ewiger Liebesrausch","beschreibung":"Kitsch-Faktor des Anwenders steigt um 300%. Effekt dauert 30 Tage an.","bild":"Artikelbilder/Artikel12.png","preis":154.99,"kategorie":"mana"},
{"name":"Energie der Natur","beschreibung":"Zieht Energie aus Pflanzen und fügt sie dir hinzu. Weniger Schlaf notwendig.","bild":"Artikelbilder/Artikel15.png","preis":319.99,"kategorie":"mana"},
{"name":"Lehre der Unendlichkeit","beschreibung":"Macht dich für immer ALLWISSEND. Und mich steinreich.","bild":"Artikelbilder/Artikel17.png","preis":99999999.99,"kategorie":"mana"}
]